righteous/__init__.py
righteous/convert.py
righteous/examples.py
righteous/quantification.py
righteous/righteous.py
righteous_fa-1.2.1.dist-info/LICENSE
righteous_fa-1.2.1.dist-info/METADATA
righteous_fa-1.2.1.dist-info/WHEEL
righteous_fa-1.2.1.dist-info/top_level.txt
righteous_fa-1.2.1.dist-info/RECORD
