Metadata-Version: 2.1
Name: righteous-fa
Version: 1.2.1
Summary: Righteous Pathway Factor Analysis
Home-page: https://github.com/richardtjornhammar/impetuous
Author: Richard Tjörnhammar
Author-email: richard.tjornhammar@gmail.com
License: UNKNOWN
Platform: UNKNOWN
Classifier: Programming Language :: Python :: 3
Classifier: License :: OSI Approved :: Apache Software License
Classifier: Operating System :: OS Independent
